gamepyd/__init__.py
gamepyd/readPad.py
gamepyd/writePad.py
gamepyd/vXboxInterface-x64/msvcp120.dll
gamepyd/vXboxInterface-x64/msvcr120.dll
gamepyd/vXboxInterface-x64/vXboxInterface.dll
gamepyd/vXboxInterface-x86/msvcp120.dll
gamepyd/vXboxInterface-x86/msvcr120.dll
gamepyd/vXboxInterface-x86/vXboxInterface.dll
gamePyd-0.1.0.dist-info/LICENSE
gamePyd-0.1.0.dist-info/METADATA
gamePyd-0.1.0.dist-info/WHEEL
gamePyd-0.1.0.dist-info/top_level.txt
gamePyd-0.1.0.dist-info/RECORD
