Metadata-Version: 2.1
Name: gamePyd
Version: 0.1.0
Summary: Read or emulate gamepads conviniently
Home-page: https://github.com/PCPLays/gamePyd
Author: Ayush Rawat (@PCplays)
Author-email: rawatayush1997@gmail.com
License: Unlicense
Keywords: virtual xbox controller xinput pyxinput
Platform: UNKNOWN
Classifier: Development Status :: 4 - Beta
Classifier: Intended Audience :: Developers
Classifier: Topic :: Software Development :: Build Tools
Classifier: License :: OSI Approved :: The Unlicense (Unlicense)
Classifier: Programming Language :: Python :: 3.7
Classifier: Programming Language :: Python :: 3.8
Classifier: Programming Language :: Python :: 3.9
Requires-Python: >=3.6
